sword_mound/__init__.py
sword_mound/converter.py
sword_mound/set_sword_mound_config.py
sword_mound/sword_mound_config_default.py
sword_mound/patch/__init__.py
sword_mound/patch/print_patch.py
sword_mound/tool/__init__.py
sword_mound/tool/decorators.py
sword_mound/tool/parse.py
sword_mound/tool/times.py
sword_mound-0.0.2.dist-info/LICENSE
sword_mound-0.0.2.dist-info/METADATA
sword_mound-0.0.2.dist-info/WHEEL
sword_mound-0.0.2.dist-info/entry_points.txt
sword_mound-0.0.2.dist-info/top_level.txt
sword_mound-0.0.2.dist-info/RECORD
